rusty_capacitance_model_core-1.4.1.dist-info/METADATA
rusty_capacitance_model_core-1.4.1.dist-info/WHEEL
rusty_capacitance_model_core-1.4.1.dist-info/license_files/LICENSE.md
rusty_capacitance_model_core/__init__.py
rusty_capacitance_model_core/rusty_capacitance_model_core.cpython-310-x86_64-linux-gnu.so
rusty_capacitance_model_core-1.4.1.dist-info/RECORD
