Metadata-Version: 2.1
Name: rusty_capacitance_model_core
Version: 1.4.1
Classifier: Topic :: Scientific/Engineering :: Physics
Classifier: Operating System :: OS Independent
Classifier: Programming Language :: Rust
Classifier: Programming Language :: Python :: Implementation :: CPython
License-File: LICENSE.md
Author-email: Barnaby van Straaten <barnaby.vanstraaten@kellogg.ox.ac.uk>
Requires-Python: >=3.10
Project-URL: Homepage, https://github.com/b-vanstraaten/rusty_capacitance_model_core
